mmar_ptag/__init__.py
mmar_ptag/io_grpc.py
mmar_ptag/logging_configuration.py
mmar_ptag/ptag_framework.py
mmar_ptag/ptag_pb2.py
mmar_ptag/ptag_pb2.pyi
mmar_ptag/ptag_pb2_grpc.py
mmar_ptag/py.typed
mmar_ptag-1.0.20.dist-info/licenses/LICENSE
mmar_ptag-1.0.20.dist-info/WHEEL
mmar_ptag-1.0.20.dist-info/METADATA
mmar_ptag-1.0.20.dist-info/RECORD
