Metadata-Version: 2.4
Name: mmar-ptag
Version: 1.0.20
Summary: pydantically-type-adapted-grpc framework for multimodal architectures team
Keywords: 
Author: Eugene Tagin
Author-email: Eugene Tagin <tagin@airi.net>
License-Expression: MIT
License-File: LICENSE
Classifier: Development Status :: 4 - Beta
Classifier: Intended Audience :: Developers
Classifier: Programming Language :: Python
Classifier: Programming Language :: Python :: 3
Classifier: Programming Language :: Python :: 3 :: Only
Classifier: Programming Language :: Python :: 3.12
Classifier: Programming Language :: Python :: 3.13
Classifier: Programming Language :: Python :: 3.14
Classifier: Topic :: Documentation
Classifier: Topic :: Software Development
Classifier: Topic :: Utilities
Classifier: Typing :: Typed
Requires-Dist: protobuf~=5.29.1
Requires-Dist: grpcio~=1.68.1
Requires-Dist: grpcio-tools~=1.68.1
Requires-Dist: loguru~=0.7.2
Requires-Dist: pydantic~=2.12.5
Requires-Dist: mmar-utils~=1.1.11
Requires-Python: >=3.11
